audeer/__init__.py
audeer/core/__init__.py
audeer/core/config.py
audeer/core/conftest.py
audeer/core/io.py
audeer/core/path.py
audeer/core/tqdm.py
audeer/core/utils.py
audeer/core/version.py
audeer-2.3.0.dist-info/licenses/LICENSE
docs/changelog.rst
docs/conf.py
docs/conftest.py
docs/contributing.rst
docs/genindex.rst
docs/index.rst
docs/installation.rst
docs/usage.rst
docs/api-src/audeer.rst
tests/test_install.py
tests/test_io.py
tests/test_path.py
tests/test_tqdm.py
tests/test_utils.py
tests/test_version.py
audeer-2.3.0.dist-info/METADATA
audeer-2.3.0.dist-info/WHEEL
audeer-2.3.0.dist-info/top_level.txt
audeer-2.3.0.dist-info/RECORD
