Metadata-Version: 2.4
Name: audeer
Version: 2.3.0
Summary: Helpful Python functions
Author-email: Hagen Wierstorf <hwierstorf@audeering.com>, Johannes Wagner <jwagner@audeering.com>
License-Expression: MIT
Project-URL: repository, https://github.com/audeering/audeer/
Project-URL: documentation, https://audeering.github.io/audeer/
Keywords: Python,tools
Classifier: Development Status :: 5 - Production/Stable
Classifier: Intended Audience :: Science/Research
Classifier: Intended Audience :: Developers
Classifier: Operating System :: OS Independent
Classifier: Programming Language :: Python
Classifier: Programming Language :: Python :: 3
Classifier: Programming Language :: Python :: 3.10
Classifier: Programming Language :: Python :: 3.11
Classifier: Programming Language :: Python :: 3.12
Classifier: Programming Language :: Python :: 3.13
Classifier: Programming Language :: Python :: 3.14
Classifier: Topic :: Utilities
Requires-Python: >=3.10
License-File: LICENSE
Requires-Dist: tqdm
Dynamic: license-file
